crosstech/__init__.py
crosstech/cloud_funcs/__init__.py
crosstech/cloud_funcs/make_request.py
crosstech/database/__init__.py
crosstech/database/database.py
crosstech/elrs/__init__.py
crosstech/elrs/full.py
crosstech/elrs/simplified.py
crosstech/location/__init__.py
crosstech/location/data/elrs.pkl
crosstech/location/explore.py
crosstech/location/loc_tools.py
crosstech/location/track_geojsons.py
crosstech/mileage/__init__.py
crosstech/mileage/miles_yards.py
crosstech_py_tools-0.4.0.dist-info/METADATA
crosstech_py_tools-0.4.0.dist-info/WHEEL
crosstech_py_tools-0.4.0.dist-info/RECORD
